durak/__init__.py
durak/cleaning.py
durak/stopwords.py
durak/tokenizer.py
durak_nlp-0.1.0.dist-info/licenses/LICENSE
durak_nlp-0.1.0.dist-info/METADATA
durak_nlp-0.1.0.dist-info/WHEEL
durak_nlp-0.1.0.dist-info/top_level.txt
durak_nlp-0.1.0.dist-info/RECORD
