Metadata-Version: 2.4
Name: durak-nlp
Version: 0.1.0
Summary: Durak: modular Turkish NLP preprocessing toolkit.
Author: Fatih Burak Karagöz
License-Expression: LicenseRef-Durak-1.0
Project-URL: Homepage, https://karagoz.io
Project-URL: Repository, https://github.com/fbkaragoz/durak
Project-URL: Issues, https://github.com/fbkaragoz/durak/issues
Keywords: turkish nlp,text processing,preprocessing,lemmatization,tokenization
Classifier: Development Status :: 3 - Alpha
Classifier: Intended Audience :: Developers
Classifier: Intended Audience :: Science/Research
Classifier: Natural Language :: Turkish
Classifier: Programming Language :: Python :: 3
Classifier: Programming Language :: Python :: 3 :: Only
Classifier: Programming Language :: Python :: 3.9
Classifier: Programming Language :: Python :: 3.10
Classifier: Programming Language :: Python :: 3.11
Classifier: Programming Language :: Python :: 3.12
Classifier: Topic :: Text Processing :: Linguistic
Requires-Python: >=3.9
License-File: LICENSE
Provides-Extra: dev
Requires-Dist: black>=24.0.0; extra == "dev"
Requires-Dist: ruff>=0.3.0; extra == "dev"
Requires-Dist: pytest>=8.0.0; extra == "dev"
Requires-Dist: coverage[toml]>=7.0.0; extra == "dev"
Dynamic: license-file
